django_user_deletion-0.2.0.dist-info/DESCRIPTION.rst
django_user_deletion-0.2.0.dist-info/METADATA
django_user_deletion-0.2.0.dist-info/RECORD
django_user_deletion-0.2.0.dist-info/WHEEL
django_user_deletion-0.2.0.dist-info/metadata.json
django_user_deletion-0.2.0.dist-info/top_level.txt
tests/__init__.py
tests/factories.py
tests/models.py
tests/run.py
tests/test_management_commands.py
tests/test_managers.py
tests/test_notifications.py
user_deletion/__init__.py
user_deletion/apps.py
user_deletion/managers.py
user_deletion/notifications.py
user_deletion/management/__init__.py
user_deletion/management/commands/__init__.py
user_deletion/management/commands/delete_users.py
user_deletion/management/commands/notify_users.py
user_deletion/templates/user_deletion/base.txt
user_deletion/templates/user_deletion/email_deletion.txt
user_deletion/templates/user_deletion/email_notification.txt
