Metadata-Version: 2.0
Name: django-user-deletion
Version: 0.2.0
Summary: Management commands to notify and delete inactive django users
Home-page: https://github.com/incuna/django-user-deletion
Author: Incuna Ltd
Author-email: admin@incuna.com
License: BSD
Platform: UNKNOWN
Classifier: Development Status :: 1 - Planning
Classifier: Framework :: Django
Classifier: Intended Audience :: Developers
Classifier: License :: OSI Approved :: BSD License
Classifier: Natural Language :: English
Classifier: Programming Language :: Python :: 3.4
Classifier: Programming Language :: Python :: 3.5
